ingot_tcp/__init__.py
ingot_tcp/bootstrap/__init__.py
ingot_tcp/bootstrap/scaffolding/__init__.py
ingot_tcp/scripts/__init__.py
ingot_tcp/scripts/ingot_tcp.py
ingot_tcp/tests/__init__.py
ingot_tcp/tests/functionals/__init__.py
ingot_tcp/tests/units/__init__.py
ingot_tcp/tests/units/scripts/__init__.py
ingot_tcp/tests/units/scripts/test_ingot_tcp.py
scripts/__init__.py
scripts/create_package_version_file.py
ingot_tcp-0.1.0.dist-info/LICENSE
ingot_tcp-0.1.0.dist-info/METADATA
ingot_tcp-0.1.0.dist-info/WHEEL
ingot_tcp-0.1.0.dist-info/entry_points.txt
ingot_tcp-0.1.0.dist-info/top_level.txt
ingot_tcp-0.1.0.dist-info/RECORD
